{
  "mode": "expert",
  "config": {
    "run_mode": "expert",
    "model_name": "efficientnet_b2",
    "pretrained": true,
    "loss": "cross_entropy",
    "epochs": 25,
    "batch_size": 16,
    "image_size": 256,
    "learning_rate": 0.0003,
    "weight_decay": 0.0001,
    "label_smoothing": 0.1,
    "focal_gamma": 2.0,
    "class_weighting": "none",
    "class_weights": null,
    "scheduler": "none",
    "min_lr": 1e-06,
    "mixup_alpha": 0.0,
    "cutmix_alpha": 0.0,
    "mix_prob": 1.0,
    "mix_switch_prob": 0.5,
    "feature_attention": "none",
    "num_workers": 0,
    "seed": 42,
    "device_request": "cuda",
    "device": "cuda",
    "amp_enabled": true,
    "deterministic": false,
    "pin_memory": true,
    "active_class_names": [
      "large.cell.carcinoma",
      "squamous.cell.carcinoma"
    ],
    "expert_classes_arg": "large.cell.carcinoma,squamous.cell.carcinoma"
  },
  "hardware": {
    "cuda_available": true,
    "gpu_name": "NVIDIA GeForce RTX 4060 Laptop GPU"
  },
  "dataset": {
    "data_dir": "C:\\Users\\梁嘉纯\\Desktop\\2026年APMCM亚太地区大学生大模型竞赛赛题\\2026年APMCM亚太地区大学生大模型竞赛赛题\\B题\\基线\\附件\\Data",
    "class_names": [
      "large.cell.carcinoma",
      "squamous.cell.carcinoma"
    ],
    "split_sizes": {
      "train": 270,
      "valid": 36,
      "test": 141
    },
    "class_distribution": {
      "train": {
        "large.cell.carcinoma": 115,
        "squamous.cell.carcinoma": 155
      },
      "valid": {
        "large.cell.carcinoma": 21,
        "squamous.cell.carcinoma": 15
      },
      "test": {
        "large.cell.carcinoma": 51,
        "squamous.cell.carcinoma": 90
      }
    }
  },
  "training_history": [
    {
      "epoch": 1,
      "train_loss": 0.5344940428380613,
      "train_accuracy": 0.7444444444444445,
      "valid_loss": 0.737116845117675,
      "valid_accuracy": 0.6111111111111112,
      "learning_rate": 0.0003
    },
    {
      "epoch": 2,
      "train_loss": 0.3040421102885847,
      "train_accuracy": 0.9444444444444444,
      "valid_loss": 0.5014143404033449,
      "valid_accuracy": 0.75,
      "learning_rate": 0.0003
    },
    {
      "epoch": 3,
      "train_loss": 0.24949507845772637,
      "train_accuracy": 0.9777777777777777,
      "valid_loss": 0.3486749827861786,
      "valid_accuracy": 0.8888888888888888,
      "learning_rate": 0.0003
    },
    {
      "epoch": 4,
      "train_loss": 0.24502072621274879,
      "train_accuracy": 0.9814814814814815,
      "valid_loss": 0.42744572626219857,
      "valid_accuracy": 0.7777777777777778,
      "learning_rate": 0.0003
    },
    {
      "epoch": 5,
      "train_loss": 0.2442004430073279,
      "train_accuracy": 0.9851851851851852,
      "valid_loss": 0.4063550564977858,
      "valid_accuracy": 0.8611111111111112,
      "learning_rate": 0.0003
    },
    {
      "epoch": 6,
      "train_loss": 0.2288185832677064,
      "train_accuracy": 0.9851851851851852,
      "valid_loss": 0.5451165719164742,
      "valid_accuracy": 0.7777777777777778,
      "learning_rate": 0.0003
    },
    {
      "epoch": 7,
      "train_loss": 0.23360349767737917,
      "train_accuracy": 0.9888888888888889,
      "valid_loss": 0.4120931857162052,
      "valid_accuracy": 0.8611111111111112,
      "learning_rate": 0.0003
    },
    {
      "epoch": 8,
      "train_loss": 0.2231307261519962,
      "train_accuracy": 0.9925925925925926,
      "valid_loss": 0.38858243491914535,
      "valid_accuracy": 0.8888888888888888,
      "learning_rate": 0.0003
    },
    {
      "epoch": 9,
      "train_loss": 0.2209215357347771,
      "train_accuracy": 0.9888888888888889,
      "valid_loss": 0.6212507519457076,
      "valid_accuracy": 0.75,
      "learning_rate": 0.0003
    },
    {
      "epoch": 10,
      "train_loss": 0.21892635314552872,
      "train_accuracy": 0.9888888888888889,
      "valid_loss": 0.6234511567486657,
      "valid_accuracy": 0.75,
      "learning_rate": 0.0003
    },
    {
      "epoch": 11,
      "train_loss": 0.21054789986875322,
      "train_accuracy": 0.9925925925925926,
      "valid_loss": 0.3534942633575863,
      "valid_accuracy": 0.8888888888888888,
      "learning_rate": 0.0003
    },
    {
      "epoch": 12,
      "train_loss": 0.22328561555456233,
      "train_accuracy": 0.9851851851851852,
      "valid_loss": 0.3252842293845283,
      "valid_accuracy": 0.8888888888888888,
      "learning_rate": 0.0003
    },
    {
      "epoch": 13,
      "train_loss": 0.21590437337204263,
      "train_accuracy": 0.9962962962962963,
      "valid_loss": 0.3858690659205119,
      "valid_accuracy": 0.9166666666666666,
      "learning_rate": 0.0003
    },
    {
      "epoch": 14,
      "train_loss": 0.21967860460281372,
      "train_accuracy": 0.9888888888888889,
      "valid_loss": 0.3782610528998905,
      "valid_accuracy": 0.8888888888888888,
      "learning_rate": 0.0003
    },
    {
      "epoch": 15,
      "train_loss": 0.208567679921786,
      "train_accuracy": 0.9962962962962963,
      "valid_loss": 0.33144134283065796,
      "valid_accuracy": 0.8888888888888888,
      "learning_rate": 0.0003
    },
    {
      "epoch": 16,
      "train_loss": 0.20716222800590373,
      "train_accuracy": 0.9925925925925926,
      "valid_loss": 0.3993367784553104,
      "valid_accuracy": 0.8333333333333334,
      "learning_rate": 0.0003
    },
    {
      "epoch": 17,
      "train_loss": 0.22259387914781217,
      "train_accuracy": 0.9814814814814815,
      "valid_loss": 0.30803367495536804,
      "valid_accuracy": 0.9166666666666666,
      "learning_rate": 0.0003
    },
    {
      "epoch": 18,
      "train_loss": 0.20867238265496713,
      "train_accuracy": 0.9962962962962963,
      "valid_loss": 0.5479244391123453,
      "valid_accuracy": 0.8611111111111112,
      "learning_rate": 0.0003
    },
    {
      "epoch": 19,
      "train_loss": 0.2066127278186657,
      "train_accuracy": 0.9962962962962963,
      "valid_loss": 0.4994319925705592,
      "valid_accuracy": 0.8333333333333334,
      "learning_rate": 0.0003
    },
    {
      "epoch": 20,
      "train_loss": 0.20762497826858803,
      "train_accuracy": 0.9925925925925926,
      "valid_loss": 0.40351802441808915,
      "valid_accuracy": 0.8611111111111112,
      "learning_rate": 0.0003
    },
    {
      "epoch": 21,
      "train_loss": 0.2043421459418756,
      "train_accuracy": 0.9962962962962963,
      "valid_loss": 0.3691116339630551,
      "valid_accuracy": 0.8611111111111112,
      "learning_rate": 0.0003
    },
    {
      "epoch": 22,
      "train_loss": 0.20478909225375563,
      "train_accuracy": 0.9962962962962963,
      "valid_loss": 0.37529289722442627,
      "valid_accuracy": 0.8611111111111112,
      "learning_rate": 0.0003
    },
    {
      "epoch": 23,
      "train_loss": 0.2088245373081278,
      "train_accuracy": 0.9962962962962963,
      "valid_loss": 0.30586525466707015,
      "valid_accuracy": 0.8888888888888888,
      "learning_rate": 0.0003
    },
    {
      "epoch": 24,
      "train_loss": 0.21865231957700518,
      "train_accuracy": 0.9888888888888889,
      "valid_loss": 0.3137587507565816,
      "valid_accuracy": 0.8888888888888888,
      "learning_rate": 0.0003
    },
    {
      "epoch": 25,
      "train_loss": 0.21420278184943728,
      "train_accuracy": 0.9925925925925926,
      "valid_loss": 0.49307801988389754,
      "valid_accuracy": 0.8333333333333334,
      "learning_rate": 0.0003
    }
  ],
  "best_epoch": 13,
  "best_validation": {
    "loss": 0.3858690659205119,
    "accuracy": 0.9166666666666666,
    "report": {
      "large.cell.carcinoma": {
        "precision": 1.0,
        "recall": 0.8571428571428571,
        "f1-score": 0.9230769230769231,
        "support": 21.0
      },
      "squamous.cell.carcinoma": {
        "precision": 0.8333333333333334,
        "recall": 1.0,
        "f1-score": 0.9090909090909091,
        "support": 15.0
      },
      "accuracy": 0.9166666666666666,
      "macro avg": {
        "precision": 0.9166666666666667,
        "recall": 0.9285714285714286,
        "f1-score": 0.916083916083916,
        "support": 36.0
      },
      "weighted avg": {
        "precision": 0.9305555555555556,
        "recall": 0.9166666666666666,
        "f1-score": 0.9172494172494174,
        "support": 36.0
      }
    }
  },
  "test": {
    "loss": 0.24986055451082,
    "accuracy": 0.9858156028368794,
    "report": {
      "large.cell.carcinoma": {
        "precision": 1.0,
        "recall": 0.9607843137254902,
        "f1-score": 0.98,
        "support": 51.0
      },
      "squamous.cell.carcinoma": {
        "precision": 0.9782608695652174,
        "recall": 1.0,
        "f1-score": 0.989010989010989,
        "support": 90.0
      },
      "accuracy": 0.9858156028368794,
      "macro avg": {
        "precision": 0.9891304347826086,
        "recall": 0.9803921568627452,
        "f1-score": 0.9845054945054945,
        "support": 141.0
      },
      "weighted avg": {
        "precision": 0.9861239592969473,
        "recall": 0.9858156028368794,
        "f1-score": 0.9857516951133972,
        "support": 141.0
      }
    }
  },
  "elapsed_seconds": 113.13603329658508
}