{
  "mode": "expert",
  "config": {
    "run_mode": "expert",
    "model_name": "efficientnet_b1",
    "pretrained": true,
    "loss": "focal",
    "epochs": 25,
    "batch_size": 16,
    "image_size": 240,
    "learning_rate": 0.0003,
    "weight_decay": 0.0001,
    "label_smoothing": 0.1,
    "focal_gamma": 2.0,
    "class_weighting": "none",
    "class_weights": null,
    "scheduler": "cosine",
    "min_lr": 1e-06,
    "mixup_alpha": 0.2,
    "cutmix_alpha": 0.0,
    "mix_prob": 1.0,
    "mix_switch_prob": 0.5,
    "feature_attention": "none",
    "num_workers": 0,
    "seed": 42,
    "device_request": "cuda",
    "device": "cuda",
    "amp_enabled": true,
    "deterministic": false,
    "pin_memory": true,
    "active_class_names": [
      "adenocarcinoma",
      "squamous.cell.carcinoma"
    ],
    "expert_classes_arg": "adenocarcinoma,squamous.cell.carcinoma"
  },
  "hardware": {
    "cuda_available": true,
    "gpu_name": "NVIDIA GeForce RTX 4060 Laptop GPU"
  },
  "dataset": {
    "data_dir": "C:\\Users\\梁嘉纯\\Desktop\\2026年APMCM亚太地区大学生大模型竞赛赛题\\2026年APMCM亚太地区大学生大模型竞赛赛题\\B题\\基线\\附件\\Data",
    "class_names": [
      "adenocarcinoma",
      "squamous.cell.carcinoma"
    ],
    "split_sizes": {
      "train": 350,
      "valid": 38,
      "test": 210
    },
    "class_distribution": {
      "train": {
        "adenocarcinoma": 195,
        "squamous.cell.carcinoma": 155
      },
      "valid": {
        "adenocarcinoma": 23,
        "squamous.cell.carcinoma": 15
      },
      "test": {
        "adenocarcinoma": 120,
        "squamous.cell.carcinoma": 90
      }
    }
  },
  "training_history": [
    {
      "epoch": 1,
      "train_loss": 0.1742359003850392,
      "train_accuracy": 0.5285714285714286,
      "valid_loss": 0.14630604888263501,
      "valid_accuracy": 0.6842105263157895,
      "learning_rate": 0.00029882114784651444
    },
    {
      "epoch": 2,
      "train_loss": 0.13968195974826814,
      "train_accuracy": 0.6514285714285715,
      "valid_loss": 0.3209232417376418,
      "valid_accuracy": 0.7105263157894737,
      "learning_rate": 0.00029530318258873034
    },
    {
      "epoch": 3,
      "train_loss": 0.10634213571037565,
      "train_accuracy": 0.6914285714285714,
      "valid_loss": 0.17459610849618912,
      "valid_accuracy": 0.6578947368421053,
      "learning_rate": 0.0002895015846402936
    },
    {
      "epoch": 4,
      "train_loss": 0.055093522369861606,
      "train_accuracy": 0.7571428571428571,
      "valid_loss": 0.14916299518785978,
      "valid_accuracy": 0.8421052631578947,
      "learning_rate": 0.0002815078486665576
    },
    {
      "epoch": 5,
      "train_loss": 0.12054628040109362,
      "train_accuracy": 0.6942857142857143,
      "valid_loss": 0.2132432023553472,
      "valid_accuracy": 0.5263157894736842,
      "learning_rate": 0.00027144804065905466
    },
    {
      "epoch": 6,
      "train_loss": 0.0985817868475403,
      "train_accuracy": 0.6942857142857143,
      "valid_loss": 0.0702734699374751,
      "valid_accuracy": 0.868421052631579,
      "learning_rate": 0.00025948080979950103
    },
    {
      "epoch": 7,
      "train_loss": 0.07844841944319861,
      "train_accuracy": 0.7542857142857143,
      "valid_loss": 0.1362145645053763,
      "valid_accuracy": 0.868421052631579,
      "learning_rate": 0.0002457948864674291
    },
    {
      "epoch": 8,
      "train_loss": 0.06165497390287263,
      "train_accuracy": 0.6857142857142857,
      "valid_loss": 0.06916183703824093,
      "valid_accuracy": 0.9210526315789473,
      "learning_rate": 0.00023060610584935994
    },
    {
      "epoch": 9,
      "train_loss": 0.049211870857647486,
      "train_accuracy": 0.7285714285714285,
      "valid_loss": 0.07598846052822314,
      "valid_accuracy": 0.868421052631579,
      "learning_rate": 0.00021415400408897832
    },
    {
      "epoch": 10,
      "train_loss": 0.02634421879691737,
      "train_accuracy": 0.6771428571428572,
      "valid_loss": 0.027461238205432892,
      "valid_accuracy": 0.9473684210526315,
      "learning_rate": 0.0001966980406590546
    },
    {
      "epoch": 11,
      "train_loss": 0.03128961671409863,
      "train_accuracy": 0.7457142857142857,
      "valid_loss": 0.04204729807220007,
      "valid_accuracy": 0.9473684210526315,
      "learning_rate": 0.00017851350653056583
    },
    {
      "epoch": 12,
      "train_loss": 0.02676960260740348,
      "train_accuracy": 0.7714285714285715,
      "valid_loss": 0.15085957179728307,
      "valid_accuracy": 0.8947368421052632,
      "learning_rate": 0.00015988718266963235
    },
    {
      "epoch": 13,
      "train_loss": 0.022211759633251598,
      "train_accuracy": 0.7085714285714285,
      "valid_loss": 0.038149446641144,
      "valid_accuracy": 0.9736842105263158,
      "learning_rate": 0.00014111281733036765
    },
    {
      "epoch": 14,
      "train_loss": 0.033570453583129815,
      "train_accuracy": 0.6571428571428571,
      "valid_loss": 0.04282449283882191,
      "valid_accuracy": 0.9473684210526315,
      "learning_rate": 0.00012248649346943417
    },
    {
      "epoch": 15,
      "train_loss": 0.015176838636398316,
      "train_accuracy": 0.7228571428571429,
      "valid_loss": 0.04468711465597153,
      "valid_accuracy": 0.9473684210526315,
      "learning_rate": 0.0001043019593409454
    },
    {
      "epoch": 16,
      "train_loss": 0.023754763709647315,
      "train_accuracy": 0.7342857142857143,
      "valid_loss": 0.025427543411129398,
      "valid_accuracy": 0.9736842105263158,
      "learning_rate": 8.684599591102163e-05
    },
    {
      "epoch": 17,
      "train_loss": 0.028409489416517317,
      "train_accuracy": 0.6514285714285715,
      "valid_loss": 0.026319127725927455,
      "valid_accuracy": 0.9736842105263158,
      "learning_rate": 7.039389415063997e-05
    },
    {
      "epoch": 18,
      "train_loss": 0.03624196675206934,
      "train_accuracy": 0.7285714285714285,
      "valid_loss": 0.053970762871597945,
      "valid_accuracy": 0.8947368421052632,
      "learning_rate": 5.520511353257088e-05
    },
    {
      "epoch": 19,
      "train_loss": 0.027632109464279242,
      "train_accuracy": 0.7714285714285715,
      "valid_loss": 0.027420041200361754,
      "valid_accuracy": 0.9473684210526315,
      "learning_rate": 4.151919020049901e-05
    },
    {
      "epoch": 20,
      "train_loss": 0.013102082969354731,
      "train_accuracy": 0.7542857142857143,
      "valid_loss": 0.02484214031382611,
      "valid_accuracy": 0.9736842105263158,
      "learning_rate": 2.9551959340945376e-05
    },
    {
      "epoch": 21,
      "train_loss": 0.02547233893402985,
      "train_accuracy": 0.7428571428571429,
      "valid_loss": 0.03251881799415538,
      "valid_accuracy": 0.9210526315789473,
      "learning_rate": 1.94921513334424e-05
    },
    {
      "epoch": 22,
      "train_loss": 0.024483914471098354,
      "train_accuracy": 0.7628571428571429,
      "valid_loss": 0.031908302126746425,
      "valid_accuracy": 0.9210526315789473,
      "learning_rate": 1.1498415359706427e-05
    },
    {
      "epoch": 23,
      "train_loss": 0.010130183358809778,
      "train_accuracy": 0.8,
      "valid_loss": 0.03395018677570318,
      "valid_accuracy": 0.9473684210526315,
      "learning_rate": 5.6968174112696716e-06
    },
    {
      "epoch": 24,
      "train_loss": 0.02338653316455228,
      "train_accuracy": 0.8571428571428571,
      "valid_loss": 0.033381150251156406,
      "valid_accuracy": 0.9473684210526315,
      "learning_rate": 2.1788521534855743e-06
    },
    {
      "epoch": 25,
      "train_loss": 0.027112863053168568,
      "train_accuracy": 0.7657142857142857,
      "valid_loss": 0.030998048323549722,
      "valid_accuracy": 0.9736842105263158,
      "learning_rate": 1e-06
    }
  ],
  "best_epoch": 13,
  "best_validation": {
    "loss": 0.038149446641144,
    "accuracy": 0.9736842105263158,
    "report": {
      "adenocarcinoma": {
        "precision": 0.9583333333333334,
        "recall": 1.0,
        "f1-score": 0.9787234042553191,
        "support": 23.0
      },
      "squamous.cell.carcinoma": {
        "precision": 1.0,
        "recall": 0.9333333333333333,
        "f1-score": 0.9655172413793104,
        "support": 15.0
      },
      "accuracy": 0.9736842105263158,
      "macro avg": {
        "precision": 0.9791666666666667,
        "recall": 0.9666666666666667,
        "f1-score": 0.9721203228173148,
        "support": 38.0
      },
      "weighted avg": {
        "precision": 0.9747807017543861,
        "recall": 0.9736842105263158,
        "f1-score": 0.9735104452253157,
        "support": 38.0
      }
    }
  },
  "test": {
    "loss": 0.10839358383700962,
    "accuracy": 0.8333333333333334,
    "report": {
      "adenocarcinoma": {
        "precision": 0.912621359223301,
        "recall": 0.7833333333333333,
        "f1-score": 0.8430493273542601,
        "support": 120.0
      },
      "squamous.cell.carcinoma": {
        "precision": 0.7570093457943925,
        "recall": 0.9,
        "f1-score": 0.8223350253807107,
        "support": 90.0
      },
      "accuracy": 0.8333333333333334,
      "macro avg": {
        "precision": 0.8348153525088468,
        "recall": 0.8416666666666667,
        "f1-score": 0.8326921763674854,
        "support": 210.0
      },
      "weighted avg": {
        "precision": 0.8459304963251975,
        "recall": 0.8333333333333334,
        "f1-score": 0.8341717693655961,
        "support": 210.0
      }
    }
  },
  "elapsed_seconds": 117.10677599906921
}